dtocean_data/__init__.py
dtocean_data-2022.7.dist-info/METADATA
dtocean_data-2022.7.dist-info/WHEEL
dtocean_data-2022.7.dist-info/RECORD
