Metadata-Version: 2.1
Name: dtocean-data
Version: 2022.7
Summary: Fetches non-code files required by the DTOcean modules.
Author: Mathew Topper
Author-email: damm_horse@yahoo.co.uk
Requires-Python: >=3.12,<4.0
Classifier: Programming Language :: Python :: 3
Classifier: Programming Language :: Python :: 3.12
Classifier: Programming Language :: Python :: 3.13
